{
    "旅馆：检查是否需要": {
        "recognition": "Custom",
        "custom_recognition": "need_to_inn",
        "pre_delay": 0,
        "post_delay": 0,
        "next": [
            "旅馆：【循环】去休息"
        ]
    },
    "旅馆：【循环】去休息": {
        "pre_delay": 0,
        "post_delay": 0,
        "next": [
            "网络错误重试",
            "旅馆：回到城镇",
            "旅馆：进入旅馆",
            "旅馆：点击住宿",
            "旅馆：点击标准房",
            "旅馆：点击确定",
            "旅馆：判断休息完成",
            "[JumpBack]对话黄箭头"
        ]
    },
    "旅馆：回到城镇": {
        "recognition": "OCR",
        "expected": "回到城镇",
        "roi": [
            468,
            768,
            113,
            38
        ],
        "action": "Click",
        "next": [
            "旅馆：【循环】去休息"
        ]
    },
    "旅馆：进入旅馆": {
        "recognition": "TemplateMatch",
        "template": [
            "common/旅馆图标-王都.png"
        ],
        "roi": [
            40,
            439,
            38,
            40
        ],
        "action": "Click",
        "next": [
            "旅馆：【循环】去休息"
        ]
    },
    "旅馆：点击住宿": {
        "recognition": "OCR",
        "expected": "住宿",
        "roi": [
            559,
            555,
            68,
            46
        ],
        "action": "Click",
        "next": [
            "旅馆：【循环】去休息"
        ]
    },
    "旅馆：点击标准房": {
        "recognition": "OCR",
        "expected": "标准房",
        "roi": [
            401,
            563,
            88,
            42
        ],
        "action": "Click",
        "next": [
            "旅馆：【循环】去休息"
        ]
    },
    "旅馆：点击确定": {
        "recognition": "OCR",
        "expected": "确定",
        "roi": [
            454,
            768,
            61,
            43
        ],
        "action": "Click",
        "next": [
            "旅馆：【循环】去休息"
        ]
    },
    "旅馆：判断休息完成": {
        "recognition": "OCR",
        "expected": "身上",
        "roi": [
            52,
            1004,
            250,
            41
        ],
        "action": "Click",
        "next": [
            "旅馆：【循环】回到主循环"
        ]
    },
    "旅馆：【循环】回到主循环": {
        "pre_delay": 0,
        "post_delay": 0,
        "next": [
            "网络错误重试",
            "旅馆：点击离开",
            "旅馆：回到主循环",
            "[JumpBack]对话黄箭头"
        ]
    },
    "旅馆：点击离开": {
        "recognition": "OCR",
        "expected": "离开",
        "roi": [
            559,
            747,
            63,
            40
        ],
        "action": "Click",
        "next": [
            "旅馆：【循环】回到主循环"
        ]
    },
    "旅馆：回到主循环": {
        "recognition": "TemplateMatch",
        "template": [
            "common/旅馆图标-王都.png"
        ],
        "roi": [
            40,
            439,
            38,
            40
        ]
    }
}